LICENSE
MANIFEST.in
README.md
requirements.txt
setup.py
pyauto/__init__.py
pyauto.openvpn.egg-info/PKG-INFO
pyauto.openvpn.egg-info/SOURCES.txt
pyauto.openvpn.egg-info/dependency_links.txt
pyauto.openvpn.egg-info/requires.txt
pyauto.openvpn.egg-info/top_level.txt
pyauto/openvpn/__init__.py
pyauto/openvpn/commands.py
pyauto/openvpn/config.py
pyauto/openvpn/connect.py