Metadata-Version: 1.0
Name: pyauto.openvpn
Version: 0.0.2a2
Summary: Implements tasks that deploy an Openvpn server
Home-page: https://github.com/adamjaso/pyauto/tree/master/openvpn
Author: Adam Jaso
Author-email: UNKNOWN
License: UNKNOWN
Platform: UNKNOWN
